{"_id":{"$oid":"599698a3c72cb067418071af"},"ownerid":"599698a3c72cb0674180719c","categoryid":"599698a3c72cb067418071a4","budget":0,"budget_avg":0,"descryption":"","completed":false,"memo":"","title":"인사장 발송 또는 감사전화","__v":0}
{"_id":{"$oid":"599698a3c72cb067418071b0"},"ownerid":"599698a3c72cb0674180719c","categoryid":"599698a3c72cb0674180719d","budget":6,"budget_avg":0,"descryption":"","completed":true,"memo":"","title":"사전조사 및 예산수립","__v":0}
{"_id":{"$oid":"599698a3c72cb067418071b1"},"ownerid":"599698a3c72cb0674180719c","categoryid":"599698a3c72cb067418071a4","budget":0,"budget_avg":0,"descryption":"","completed":false,"memo":"","title":"도와주신 분들 찾아뵙기","__v":0}
{"_id":{"$oid":"599698a3c72cb067418071b2"},"ownerid":"599698a3c72cb0674180719c","categoryid":"599698a3c72cb067418071a5","budget":0,"budget_avg":0,"descryption":"","completed":false,"memo":"","title":"장소섭외","__v":0}
{"_id":{"$oid":"599698a3c72cb067418071b3"},"ownerid":"599698a3c72cb0674180719c","categoryid":"599698a3c72cb067418071a5","budget":0,"budget_avg":0,"descryption":"","completed":false,"memo":"","title":"가능한 날짜 조율","__v":0}
{"_id":{"$oid":"599698a3c72cb067418071b4"},"ownerid":"599698a3c72cb0674180719c","categoryid":"599698a3c72cb067418071a5","budget":0,"budget_avg":0,"descryption":"","completed":false,"memo":"","title":"참석자 명단 조율","__v":0}
{"_id":{"$oid":"599698a3c72cb067418071b5"},"ownerid":"599698a3c72cb0674180719c","categoryid":"599698a3c72cb067418071a0","budget":30,"budget_avg":0,"descryption":"","completed":false,"memo":"","title":"주례자 섭외","__v":0}
{"_id":{"$oid":"599698a3c72cb067418071b6"},"ownerid":"599698a3c72cb0674180719c","categoryid":"599698a3c72cb067418071a0","budget":0,"budget_avg":0,"descryption":"","completed":false,"memo":"","title":"사회자 섭외","__v":0}
{"_id":{"$oid":"599698a3c72cb067418071b7"},"ownerid":"599698a3c72cb0674180719c","categoryid":"599698a3c72cb067418071a0","budget":0,"budget_avg":0,"descryption":"","completed":false,"memo":"","title":"사진촬영 담당섭외","__v":0}
{"_id":{"$oid":"599698a3c72cb067418071b8"},"ownerid":"599698a3c72cb0674180719c","categoryid":"599698a3c72cb067418071a0","budget":0,"budget_avg":0,"descryption":"","completed":false,"memo":"","title":"비디오 촬영담당 섭외","__v":0}
{"_id":{"$oid":"599698a3c72cb067418071b9"},"ownerid":"599698a3c72cb0674180719c","categoryid":"599698a3c72cb067418071a0","budget":0,"budget_avg":0,"descryption":"","completed":false,"memo":"","title":"축가 섭외","__v":0}
{"_id":{"$oid":"599698a3c72cb067418071ba"},"ownerid":"599698a3c72cb0674180719c","categoryid":"599698a3c72cb067418071a0","budget":0,"budget_avg":0,"descryption":"","completed":false,"memo":"","title":"화동섭외","__v":0}
{"_id":{"$oid":"599698a3c72cb067418071bb"},"ownerid":"599698a3c72cb0674180719c","categoryid":"599698a3c72cb067418071a0","budget":0,"budget_avg":0,"descryption":"","completed":false,"memo":"","title":"들러리 섭외","__v":0}
{"_id":{"$oid":"599698a3c72cb067418071bc"},"ownerid":"599698a3c72cb0674180719c","categoryid":"599698a3c72cb067418071a0","budget":0,"budget_avg":0,"descryption":"","completed":false,"memo":"","title":"축의금 접수자 섭외","__v":0}
{"_id":{"$oid":"599698a3c72cb067418071bd"},"ownerid":"599698a3c72cb0674180719c","categoryid":"599698a3c72cb067418071a0","budget":0,"budget_avg":0,"descryption":"","completed":false,"memo":"","title":"신랑 도우미 섭외","__v":0}
{"_id":{"$oid":"599698a3c72cb067418071be"},"ownerid":"599698a3c72cb0674180719c","categoryid":"599698a3c72cb067418071a0","budget":0,"budget_avg":0,"descryption":"","completed":false,"memo":"","title":"신부 도우미 섭외","__v":0}
{"_id":{"$oid":"599698a3c72cb067418071bf"},"ownerid":"599698a3c72cb0674180719c","categoryid":"599698a3c72cb067418071a0","budget":0,"budget_avg":0,"descryption":"","completed":false,"memo":"","title":"웨딩카 준비","__v":0}
{"_id":{"$oid":"599698a3c72cb067418071c0"},"ownerid":"599698a3c72cb0674180719c","categoryid":"599698a3c72cb067418071a0","budget":0,"budget_avg":0,"descryption":"","completed":false,"memo":"","title":"피로연 담당자 섭외","__v":0}
{"_id":{"$oid":"599698a3c72cb067418071c1"},"ownerid":"599698a3c72cb0674180719c","categoryid":"599698a3c72cb067418071a0","budget":0,"budget_avg":0,"descryption":"","completed":false,"memo":"","title":"신부 의상 및 소품준비","__v":0}
{"_id":{"$oid":"599698a3c72cb067418071c2"},"ownerid":"599698a3c72cb0674180719c","categoryid":"599698a3c72cb067418071a0","budget":0,"budget_avg":0,"descryption":"","completed":false,"memo":"","title":"신랑 의상 및 소품준비","__v":0}
{"_id":{"$oid":"599698a3c72cb067418071c3"},"ownerid":"599698a3c72cb0674180719c","categoryid":"599698a3c72cb067418071a0","budget":0,"budget_avg":0,"descryption":"","completed":false,"memo":"","title":"답례품 준비","__v":0}
{"_id":{"$oid":"599698a3c72cb067418071c4"},"ownerid":"599698a3c72cb0674180719c","categoryid":"599698a3c72cb067418071a0","budget":0,"budget_avg":0,"descryption":"","completed":false,"memo":"","title":"방명록 및 필기도구","__v":0}
{"_id":{"$oid":"599698a3c72cb067418071c5"},"ownerid":"599698a3c72cb0674180719c","categoryid":"599698a3c72cb067418071a0","budget":0,"budget_avg":0,"descryption":"","completed":false,"memo":"","title":"축의금 접수노트 및 봉투","__v":0}
{"_id":{"$oid":"599698a3c72cb067418071c6"},"ownerid":"599698a3c72cb0674180719c","categoryid":"599698a3c72cb067418071a0","budget":0,"budget_avg":0,"descryption":"","completed":false,"memo":"","title":"사례비 준비","__v":0}
{"_id":{"$oid":"599698a3c72cb067418071c7"},"ownerid":"599698a3c72cb0674180719c","categoryid":"599698a3c72cb067418071a0","budget":0,"budget_avg":0,"descryption":"","completed":false,"memo":"","title":"주차권","__v":0}
{"_id":{"$oid":"599698a3c72cb067418071c8"},"ownerid":"599698a3c72cb0674180719c","categoryid":"599698a3c72cb067418071a0","budget":0,"budget_avg":0,"descryption":"","completed":false,"memo":"","title":"식권","__v":0}
{"_id":{"$oid":"599698a3c72cb067418071c9"},"ownerid":"599698a3c72cb0674180719c","categoryid":"599698a3c72cb067418071a0","budget":15,"budget_avg":0,"descryption":"","completed":false,"memo":"","title":"부케","__v":0}
{"_id":{"$oid":"599698a3c72cb067418071ca"},"ownerid":"599698a3c72cb0674180719c","categoryid":"599698a3c72cb067418071a0","budget":0,"budget_avg":0,"descryption":"","completed":false,"memo":"","title":"화동 및 들러리 부케","__v":0}
{"_id":{"$oid":"599698a3c72cb067418071cb"},"ownerid":"599698a3c72cb0674180719c","categoryid":"599698a3c72cb067418071a0","budget":0,"budget_avg":0,"descryption":"","completed":false,"memo":"","title":"예물반지 준비","__v":0}
{"_id":{"$oid":"599698a3c72cb067418071cc"},"ownerid":"599698a3c72cb0674180719c","categoryid":"599698a3c72cb067418071a0","budget":0,"budget_avg":0,"descryption":"","completed":false,"memo":"","title":"폐백 의상","__v":0}
{"_id":{"$oid":"599698a3c72cb067418071cd"},"ownerid":"599698a3c72cb0674180719c","categoryid":"599698a3c72cb067418071a0","budget":0,"budget_avg":0,"descryption":"","completed":false,"memo":"","title":"폐백 음식","__v":0}
{"_id":{"$oid":"599698a3c72cb067418071ce"},"ownerid":"599698a3c72cb0674180719c","categoryid":"599698a3c72cb067418071a0","budget":0,"budget_avg":0,"descryption":"","completed":false,"memo":"","title":"폐백 도우미","__v":0}
{"_id":{"$oid":"599698a3c72cb067418071cf"},"ownerid":"599698a3c72cb0674180719c","categoryid":"599698a3c72cb067418071a0","budget":0,"budget_avg":0,"descryption":"","completed":false,"memo":"","title":"흰장갑","__v":0}
{"_id":{"$oid":"599698a3c72cb067418071d0"},"ownerid":"599698a3c72cb0674180719c","categoryid":"599698a3c72cb067418071a0","budget":0,"budget_avg":0,"descryption":"","completed":false,"memo":"","title":"성혼 선언문","__v":0}
{"_id":{"$oid":"599698a3c72cb067418071d1"},"ownerid":"599698a3c72cb0674180719c","categoryid":"599698a3c72cb067418071a6","budget":0,"budget_avg":0,"descryption":"","completed":false,"memo":"","title":"장소 및 기간 계획","__v":0}
{"_id":{"$oid":"599698a3c72cb067418071d2"},"ownerid":"599698a3c72cb0674180719c","categoryid":"599698a3c72cb067418071a6","budget":0,"budget_avg":0,"descryption":"","completed":false,"memo":"","title":"예산 계획","__v":0}
{"_id":{"$oid":"599698a3c72cb067418071d3"},"ownerid":"599698a3c72cb0674180719c","categoryid":"599698a3c72cb067418071a6","budget":0,"budget_avg":0,"descryption":"","completed":false,"memo":"","title":"여권 준비 및 유효기간 확인","__v":0}
{"_id":{"$oid":"599698a3c72cb067418071d4"},"ownerid":"599698a3c72cb0674180719c","categoryid":"599698a3c72cb067418071a6","budget":0,"budget_avg":0,"descryption":"","completed":false,"memo":"","title":"비자 필요여부 확인","__v":0}
{"_id":{"$oid":"599698a3c72cb067418071d5"},"ownerid":"599698a3c72cb0674180719c","categoryid":"599698a3c72cb067418071a6","budget":0,"budget_avg":0,"descryption":"","completed":false,"memo":"","title":"신혼여행 준비물 리스트작성","__v":0}
{"_id":{"$oid":"599698a3c72cb067418071d6"},"ownerid":"599698a3c72cb0674180719c","categoryid":"599698a3c72cb067418071a6","budget":0,"budget_avg":0,"descryption":"","completed":false,"memo":"","title":"신용카드 필요여부 확인","__v":0}
{"_id":{"$oid":"599698a3c72cb067418071d7"},"ownerid":"599698a3c72cb0674180719c","categoryid":"599698a3c72cb067418071a6","budget":0,"budget_avg":0,"descryption":"","completed":false,"memo":"","title":"선물 목록 작성","__v":0}
{"_id":{"$oid":"599698a3c72cb067418071d8"},"ownerid":"599698a3c72cb0674180719c","categoryid":"599698a3c72cb067418071a6","budget":0,"budget_avg":0,"descryption":"","completed":false,"memo":"","title":"신혼 여행 짐싸기","__v":0}
{"_id":{"$oid":"599698a3c72cb067418071d9"},"ownerid":"599698a3c72cb0674180719c","categoryid":"599698a3c72cb067418071a6","budget":0,"budget_avg":0,"descryption":"","completed":false,"memo":"","title":"환전 및 현금 준비","__v":0}
{"_id":{"$oid":"599698a3c72cb067418071da"},"ownerid":"599698a3c72cb0674180719c","categoryid":"599698a3c72cb067418071a5","budget":0,"budget_avg":0,"descryption":"","completed":false,"memo":"","title":"상견례에서 결혼 날짜 및 장소 조율","__v":0}
{"_id":{"$oid":"599698a3c72cb067418071db"},"ownerid":"599698a3c72cb0674180719c","categoryid":"599698a3c72cb067418071a4","budget":0,"budget_avg":0,"descryption":"","completed":false,"memo":"","title":"가족들 방문","__v":0}
{"_id":{"$oid":"599698a3c72cb067418071dc"},"ownerid":"599698a3c72cb0674180719c","categoryid":"599698a3c72cb067418071a4","budget":0,"budget_avg":0,"descryption":"","completed":false,"memo":"","title":"이바지 음식 준비","__v":0}
{"_id":{"$oid":"599698a3c72cb067418071dd"},"ownerid":"599698a3c72cb0674180719c","categoryid":"599698a3c72cb067418071a7","budget":0,"budget_avg":0,"descryption":"","completed":false,"memo":"","title":"직장에 휴가서 제출","__v":0}
{"_id":{"$oid":"599698a3c72cb067418071de"},"ownerid":"599698a3c72cb0674180719c","categoryid":"599698a3c72cb067418071a7","budget":0,"budget_avg":0,"descryption":"","completed":false,"memo":"","title":"혼인신고","__v":0}
{"_id":{"$oid":"599698a3c72cb067418071df"},"ownerid":"599698a3c72cb0674180719c","categoryid":"599698a3c72cb067418071a7","budget":0,"budget_avg":0,"descryption":"","completed":false,"memo":"","title":"주소지 변경(의료 보험 및 운전면허등)","__v":0}
{"_id":{"$oid":"599698a3c72cb067418071e0"},"ownerid":"599698a3c72cb0674180719c","categoryid":"599698a3c72cb067418071a8","budget":0,"budget_avg":0,"descryption":"","completed":false,"memo":"","title":"결혼식장 사전조사","__v":0}
{"_id":{"$oid":"599698a3c72cb067418071e1"},"ownerid":"599698a3c72cb0674180719c","categoryid":"599698a3c72cb067418071a8","budget":0,"budget_avg":0,"descryption":"","completed":false,"memo":"","title":"결정 및 예약","__v":0}
{"_id":{"$oid":"599698a3c72cb067418071e2"},"ownerid":"599698a3c72cb0674180719c","categoryid":"599698a3c72cb067418071a8","budget":0,"budget_avg":0,"descryption":"","completed":false,"memo":"","title":"대중 교통편 확인","__v":0}
{"_id":{"$oid":"599698a3c72cb067418071e3"},"ownerid":"599698a3c72cb0674180719c","categoryid":"599698a3c72cb067418071a8","budget":0,"budget_avg":0,"descryption":"","completed":false,"memo":"","title":"주차공간 확보","__v":0}
{"_id":{"$oid":"599698a3c72cb067418071e4"},"ownerid":"599698a3c72cb0674180719c","categoryid":"599698a3c72cb067418071a8","budget":0,"budget_avg":0,"descryption":"","completed":false,"memo":"","title":"무료 제공 서비스 확인","__v":0}
{"_id":{"$oid":"599698a3c72cb067418071e5"},"ownerid":"599698a3c72cb0674180719c","categoryid":"599698a3c72cb067418071a8","budget":0,"budget_avg":0,"descryption":"","completed":false,"memo":"","title":"식장 사용료 확인","__v":0}
{"_id":{"$oid":"599698a3c72cb067418071e6"},"ownerid":"599698a3c72cb0674180719c","categoryid":"599698a3c72cb067418071a8","budget":0,"budget_avg":0,"descryption":"","completed":false,"memo":"","title":"폐백실 사용료 확인","__v":0}
{"_id":{"$oid":"599698a3c72cb067418071e7"},"ownerid":"599698a3c72cb0674180719c","categoryid":"599698a3c72cb067418071a8","budget":0,"budget_avg":0,"descryption":"","completed":false,"memo":"","title":"피로연장 사용료 확인","__v":0}
{"_id":{"$oid":"599698a3c72cb067418071e8"},"ownerid":"599698a3c72cb0674180719c","categoryid":"599698a3c72cb067418071a8","budget":0,"budget_avg":0,"descryption":"","completed":false,"memo":"","title":"피로연 음식가격","__v":0}
{"_id":{"$oid":"599698a3c72cb067418071e9"},"ownerid":"599698a3c72cb0674180719c","categoryid":"599698a3c72cb067418071a8","budget":0,"budget_avg":0,"descryption":"","completed":false,"memo":"","title":"피로연장 수용인원 확인","__v":0}
{"_id":{"$oid":"599698a3c72cb067418071ea"},"ownerid":"599698a3c72cb0674180719c","categoryid":"599698a3c72cb067418071a8","budget":0,"budget_avg":0,"descryption":"","completed":false,"memo":"","title":"피로연장 수용인원 확인","__v":0}
{"_id":{"$oid":"599698a3c72cb067418071eb"},"ownerid":"599698a3c72cb0674180719c","categoryid":"599698a3c72cb067418071a8","budget":0,"budget_avg":0,"descryption":"","completed":false,"memo":"","title":"예식 날짜 및 시간 확인","__v":0}
{"_id":{"$oid":"599698a3c72cb067418071ec"},"ownerid":"599698a3c72cb0674180719c","categoryid":"599698a3c72cb067418071a8","budget":0,"budget_avg":0,"descryption":"","completed":false,"memo":"","title":"연락처 확인","__v":0}
{"_id":{"$oid":"599698a3c72cb067418071ed"},"ownerid":"599698a3c72cb0674180719c","categoryid":"599698a3c72cb067418071a8","budget":0,"budget_avg":0,"descryption":"","completed":false,"memo":"","title":"예식장 수용인원 확인","__v":0}
{"_id":{"$oid":"599698a3c72cb067418071ee"},"ownerid":"599698a3c72cb0674180719c","categoryid":"599698a3c72cb067418071a8","budget":0,"budget_avg":0,"descryption":"","completed":false,"memo":"","title":"피로연 음식 메뉴 확인 또는 시식","__v":0}
{"_id":{"$oid":"599698a3c72cb067418071ef"},"ownerid":"599698a3c72cb0674180719c","categoryid":"599698a3c72cb067418071a9","budget":0,"budget_avg":0,"descryption":"","completed":false,"memo":"","title":"사전 조사","__v":0}
{"_id":{"$oid":"599698a3c72cb067418071f0"},"ownerid":"599698a3c72cb0674180719c","categoryid":"599698a3c72cb067418071a9","budget":0,"budget_avg":0,"descryption":"","completed":false,"memo":"","title":"신부 헤어 내용 확인","__v":0}
{"_id":{"$oid":"599698a3c72cb067418071f1"},"ownerid":"599698a3c72cb0674180719c","categoryid":"599698a3c72cb067418071a9","budget":0,"budget_avg":0,"descryption":"","completed":false,"memo":"","title":"신랑 헤어 내용 확인","__v":0}
{"_id":{"$oid":"599698a3c72cb067418071f2"},"ownerid":"599698a3c72cb0674180719c","categoryid":"599698a3c72cb067418071a9","budget":0,"budget_avg":0,"descryption":"","completed":false,"memo":"","title":"신랑 메이크업 내용확인","__v":0}
{"_id":{"$oid":"599698a3c72cb067418071f3"},"ownerid":"599698a3c72cb0674180719c","categoryid":"599698a3c72cb067418071a9","budget":0,"budget_avg":0,"descryption":"","completed":false,"memo":"","title":"신부 메이크업 내용확인","__v":0}
{"_id":{"$oid":"599698a3c72cb067418071f4"},"ownerid":"599698a3c72cb0674180719c","categoryid":"599698a3c72cb067418071a9","budget":0,"budget_avg":0,"descryption":"","completed":false,"memo":"","title":"가족 헤어 내용확인","__v":0}
{"_id":{"$oid":"599698a3c72cb067418071f5"},"ownerid":"599698a3c72cb0674180719c","categoryid":"599698a3c72cb067418071a9","budget":0,"budget_avg":0,"descryption":"","completed":false,"memo":"","title":"가족 메이크업 내용확인","__v":0}
{"_id":{"$oid":"599698a3c72cb067418071f6"},"ownerid":"599698a3c72cb0674180719c","categoryid":"599698a3c72cb067418071a9","budget":0,"budget_avg":0,"descryption":"","completed":false,"memo":"","title":"폐백 헤어 및 메이크업","__v":0}
{"_id":{"$oid":"599698a3c72cb067418071f7"},"ownerid":"599698a3c72cb0674180719c","categoryid":"599698a3c72cb067418071a9","budget":0,"budget_avg":0,"descryption":"","completed":false,"memo":"","title":"결혼식 당일 헤어 및 메이크업","__v":0}
{"_id":{"$oid":"599698a3c72cb067418071f8"},"ownerid":"599698a3c72cb0674180719c","categoryid":"599698a3c72cb067418071a9","budget":0,"budget_avg":0,"descryption":"","completed":false,"memo":"","title":"기본 가격 및 추가비용확인","__v":0}
{"_id":{"$oid":"599698a3c72cb067418071f9"},"ownerid":"599698a3c72cb0674180719c","categoryid":"599698a3c72cb067418071a9","budget":0,"budget_avg":0,"descryption":"","completed":false,"memo":"","title":"연락처 및 위치 확인","__v":0}
{"_id":{"$oid":"599698a3c72cb067418071fa"},"ownerid":"599698a3c72cb0674180719c","categoryid":"599698a3c72cb067418071a9","budget":0,"budget_avg":0,"descryption":"","completed":false,"memo":"","title":"피로연 헤어 및 메이크업","__v":0}
{"_id":{"$oid":"599698a3c72cb067418071fb"},"ownerid":"599698a3c72cb0674180719c","categoryid":"599698a3c72cb067418071aa","budget":0,"budget_avg":0,"descryption":"","completed":false,"memo":"","title":"사전 조사 및 예산짜기","__v":0}
{"_id":{"$oid":"599698a3c72cb067418071fc"},"ownerid":"599698a3c72cb0674180719c","categoryid":"599698a3c72cb067418071aa","budget":0,"budget_avg":0,"descryption":"","completed":false,"memo":"","title":"본식 드레스 확인","__v":0}
{"_id":{"$oid":"599698a3c72cb067418071fd"},"ownerid":"599698a3c72cb0674180719c","categoryid":"599698a3c72cb067418071aa","budget":0,"budget_avg":0,"descryption":"","completed":false,"memo":"","title":"스튜디오 촬영용 드레스 확인","__v":0}
{"_id":{"$oid":"599698a3c72cb067418071fe"},"ownerid":"599698a3c72cb0674180719c","categoryid":"599698a3c72cb067418071aa","budget":0,"budget_avg":0,"descryption":"","completed":false,"memo":"","title":"본식 턱시도 확인","__v":0}
{"_id":{"$oid":"599698a3c72cb067418071ff"},"ownerid":"599698a3c72cb0674180719c","categoryid":"599698a3c72cb067418071aa","budget":0,"budget_avg":0,"descryption":"","completed":false,"memo":"","title":"스튜디오 촬영용 턱시도 확인","__v":0}
{"_id":{"$oid":"599698a3c72cb06741807200"},"ownerid":"599698a3c72cb0674180719c","categoryid":"599698a3c72cb067418071aa","budget":0,"budget_avg":0,"descryption":"","completed":false,"memo":"","title":"가봉 일자 확인","__v":0}
{"_id":{"$oid":"599698a3c72cb06741807201"},"ownerid":"599698a3c72cb0674180719c","categoryid":"599698a3c72cb067418071aa","budget":0,"budget_avg":0,"descryption":"","completed":false,"memo":"","title":"악세서리 및 소품 확인","__v":0}
{"_id":{"$oid":"599698a3c72cb06741807202"},"ownerid":"599698a3c72cb0674180719c","categoryid":"599698a3c72cb067418071aa","budget":0,"budget_avg":0,"descryption":"","completed":false,"memo":"","title":"주소 및 연락처 확인","__v":0}
{"_id":{"$oid":"599698a3c72cb06741807203"},"ownerid":"599698a3c72cb0674180719c","categoryid":"599698a3c72cb0674180719d","budget":112,"budget_avg":0,"descryption":"","completed":false,"memo":"","title":"사진 총 몇 장 인지 확인","__v":0}
{"_id":{"$oid":"599698a3c72cb06741807204"},"ownerid":"599698a3c72cb0674180719c","categoryid":"599698a3c72cb0674180719d","budget":0,"budget_avg":0,"descryption":"","completed":false,"memo":"","title":"앨범은 몇권?","__v":0}
{"_id":{"$oid":"599698a3c72cb06741807205"},"ownerid":"599698a3c72cb0674180719c","categoryid":"599698a3c72cb0674180719d","budget":0,"budget_avg":0,"descryption":"","completed":false,"memo":"","title":"앨범 및 액자 스타일 확인","__v":0}
{"_id":{"$oid":"599698a3c72cb06741807206"},"ownerid":"599698a3c72cb0674180719c","categoryid":"599698a3c72cb0674180719d","budget":0,"budget_avg":0,"descryption":"","completed":false,"memo":"","title":"앨범 액자 받는 수령 날짜 확인","__v":0}
{"_id":{"$oid":"599698a3c72cb06741807207"},"ownerid":"599698a3c72cb0674180719c","categoryid":"599698a3c72cb0674180719d","budget":144,"budget_avg":0,"descryption":"","completed":false,"memo":"","title":"예약 및 잔금지불 조건 확인","__v":0}
{"_id":{"$oid":"599698a3c72cb06741807208"},"ownerid":"599698a3c72cb0674180719c","categoryid":"599698a3c72cb0674180719d","budget":0,"budget_avg":0,"descryption":"","completed":false,"memo":"","title":"드레스 및 턱시도 포함여부 확인","__v":0}
{"_id":{"$oid":"599698a3c72cb06741807209"},"ownerid":"599698a3c72cb0674180719c","categoryid":"599698a3c72cb0674180719d","budget":0,"budget_avg":0,"descryption":"","completed":false,"memo":"","title":"야외 촬영 여부 확인","__v":0}
{"_id":{"$oid":"599698a3c72cb0674180720a"},"ownerid":"599698a3c72cb0674180719c","categoryid":"599698a3c72cb0674180719d","budget":0,"budget_avg":0,"descryption":"","completed":false,"memo":"","title":"예식 촬영여부 확인","__v":0}
{"_id":{"$oid":"599698a3c72cb0674180720b"},"ownerid":"599698a3c72cb0674180719c","categoryid":"599698a3c72cb0674180719d","budget":0,"budget_avg":0,"descryption":"","completed":false,"memo":"","title":"헤어 및 메이크업 포함여부 확인","__v":0}
{"_id":{"$oid":"599698a3c72cb0674180720c"},"ownerid":"599698a3c72cb0674180719c","categoryid":"599698a3c72cb0674180719d","budget":0,"budget_avg":0,"descryption":"","completed":false,"memo":"","title":"촬영 날짜 확정","__v":0}
{"_id":{"$oid":"599698a3c72cb0674180720d"},"ownerid":"599698a3c72cb0674180719c","categoryid":"599698a3c72cb067418071ae","budget":0,"budget_avg":0,"descryption":"","completed":false,"memo":"","title":"현금만/현물만/섞어서인지 확인","__v":0}
{"_id":{"$oid":"599698a3c72cb0674180720e"},"ownerid":"599698a3c72cb0674180719c","categoryid":"599698a3c72cb067418071ae","budget":0,"budget_avg":0,"descryption":"","completed":false,"memo":"","title":"예단 보내는 날짜 정하기","__v":0}
{"_id":{"$oid":"599698a3c72cb0674180720f"},"ownerid":"599698a3c72cb0674180719c","categoryid":"599698a3c72cb067418071ae","budget":15,"budget_avg":0,"descryption":"","completed":false,"memo":"","title":"현금","__v":0}
{"_id":{"$oid":"599698a3c72cb06741807210"},"ownerid":"599698a3c72cb0674180719c","categoryid":"599698a3c72cb067418071ae","budget":0,"budget_avg":0,"descryption":"","completed":false,"memo":"","title":"서식지","__v":0}
{"_id":{"$oid":"599698a3c72cb06741807211"},"ownerid":"599698a3c72cb0674180719c","categoryid":"599698a3c72cb067418071ae","budget":0,"budget_avg":0,"descryption":"","completed":false,"memo":"","title":"예단 편지","__v":0}
{"_id":{"$oid":"599698a3c72cb06741807212"},"ownerid":"599698a3c72cb0674180719c","categoryid":"599698a3c72cb067418071ae","budget":0,"budget_avg":0,"descryption":"","completed":false,"memo":"","title":"봉채편지","__v":0}
{"_id":{"$oid":"599698a3c72cb06741807213"},"ownerid":"599698a3c72cb0674180719c","categoryid":"599698a3c72cb067418071ae","budget":0,"budget_avg":0,"descryption":"","completed":false,"memo":"","title":"은수저","__v":0}
{"_id":{"$oid":"599698a3c72cb06741807214"},"ownerid":"599698a3c72cb0674180719c","categoryid":"599698a3c72cb067418071ae","budget":0,"budget_avg":0,"descryption":"","completed":false,"memo":"","title":"반상기","__v":0}
{"_id":{"$oid":"599698a3c72cb06741807215"},"ownerid":"599698a3c72cb0674180719c","categoryid":"599698a3c72cb067418071ae","budget":0,"budget_avg":0,"descryption":"","completed":false,"memo":"","title":"이부자리","__v":0}
{"_id":{"$oid":"599698a3c72cb06741807216"},"ownerid":"599698a3c72cb0674180719c","categoryid":"599698a3c72cb067418071ae","budget":0,"budget_avg":0,"descryption":"","completed":false,"memo":"","title":"한복","__v":0}
{"_id":{"$oid":"599698a3c72cb06741807217"},"ownerid":"599698a3c72cb0674180719c","categoryid":"599698a3c72cb067418071ae","budget":0,"budget_avg":0,"descryption":"","completed":false,"memo":"","title":"귀금속","__v":0}
{"_id":{"$oid":"599698a3c72cb06741807218"},"ownerid":"599698a3c72cb0674180719c","categoryid":"599698a3c72cb067418071ae","budget":0,"budget_avg":0,"descryption":"","completed":false,"memo":"","title":"양복","__v":0}
{"_id":{"$oid":"599698a3c72cb06741807219"},"ownerid":"599698a3c72cb0674180719c","categoryid":"599698a3c72cb067418071a1","budget":0,"budget_avg":0,"descryption":"","completed":false,"memo":"","title":"다이아몬드 반지","__v":0}
{"_id":{"$oid":"599698a3c72cb0674180721a"},"ownerid":"599698a3c72cb0674180719c","categoryid":"599698a3c72cb067418071a1","budget":0,"budget_avg":0,"descryption":"","completed":false,"memo":"","title":"커플링","__v":0}
{"_id":{"$oid":"599698a3c72cb0674180721b"},"ownerid":"599698a3c72cb0674180719c","categoryid":"599698a3c72cb067418071a1","budget":0,"budget_avg":0,"descryption":"","completed":false,"memo":"","title":"커플시계","__v":0}
{"_id":{"$oid":"599698a3c72cb0674180721c"},"ownerid":"599698a3c72cb0674180719c","categoryid":"599698a3c72cb067418071a1","budget":0,"budget_avg":0,"descryption":"","completed":false,"memo":"","title":"양가 예물 집안풍습 확인","__v":0}
{"_id":{"$oid":"599698a3c72cb0674180721d"},"ownerid":"599698a3c72cb0674180719c","categoryid":"599698a3c72cb067418071a1","budget":0,"budget_avg":0,"descryption":"","completed":false,"memo":"","title":"사전 조사 및 예산 수립","__v":0}
{"_id":{"$oid":"599698a3c72cb0674180721e"},"ownerid":"599698a3c72cb0674180719c","categoryid":"599698a3c72cb067418071a3","budget":0,"budget_avg":0,"descryption":"","completed":false,"memo":"","title":"함 들이는/보내는 날짜 정하기","__v":0}
{"_id":{"$oid":"599698a3c72cb0674180721f"},"ownerid":"599698a3c72cb0674180719c","categoryid":"599698a3c72cb067418071a3","budget":0,"budget_avg":0,"descryption":"","completed":false,"memo":"","title":"양가 풍습 확인","__v":0}
{"_id":{"$oid":"599698a3c72cb06741807220"},"ownerid":"599698a3c72cb0674180719c","categoryid":"599698a3c72cb067418071a2","budget":0,"budget_avg":0,"descryption":"","completed":false,"memo":"","title":"신혼살림 목록작성","__v":0}
{"_id":{"$oid":"599698a3c72cb06741807221"},"ownerid":"599698a3c72cb0674180719c","categoryid":"599698a3c72cb067418071a2","budget":0,"budget_avg":0,"descryption":"","completed":false,"memo":"","title":"예산 수립","__v":0}
{"_id":{"$oid":"599698a3c72cb06741807222"},"ownerid":"599698a3c72cb0674180719c","categoryid":"599698a3c72cb067418071ab","budget":0,"budget_avg":0,"descryption":"","completed":false,"memo":"","title":"시장조사","__v":0}
{"_id":{"$oid":"599698a3c72cb06741807223"},"ownerid":"599698a3c72cb0674180719c","categoryid":"599698a3c72cb067418071ab","budget":0,"budget_avg":0,"descryption":"","completed":false,"memo":"","title":"청접장 초대인사 정하기","__v":0}
{"_id":{"$oid":"599698a3c72cb06741807224"},"ownerid":"599698a3c72cb0674180719c","categoryid":"599698a3c72cb067418071ab","budget":0,"budget_avg":0,"descryption":"","completed":false,"memo":"","title":"초청 목록 작성","__v":0}
{"_id":{"$oid":"599698a3c72cb06741807225"},"ownerid":"599698a3c72cb0674180719c","categoryid":"599698a3c72cb067418071ab","budget":0,"budget_avg":0,"descryption":"","completed":false,"memo":"","title":"청첩장 주문","__v":0}
{"_id":{"$oid":"599698a3c72cb06741807226"},"ownerid":"599698a3c72cb0674180719c","categoryid":"599698a3c72cb067418071ab","budget":0,"budget_avg":0,"descryption":"","completed":false,"memo":"","title":"청첩장 발송","__v":0}
{"_id":{"$oid":"599698a3c72cb06741807227"},"ownerid":"599698a3c72cb0674180719c","categoryid":"599698a3c72cb0674180719e","budget":10,"budget_avg":0,"descryption":"","completed":false,"memo":"","title":"가스설치","__v":0}
{"_id":{"$oid":"599698a3c72cb06741807228"},"ownerid":"599698a3c72cb0674180719c","categoryid":"599698a3c72cb0674180719e","budget":5,"budget_avg":0,"descryption":"","completed":false,"memo":"","title":"우편물 주소 변경","__v":0}
{"_id":{"$oid":"599698a3c72cb06741807229"},"ownerid":"599698a3c72cb0674180719c","categoryid":"599698a3c72cb0674180719e","budget":0,"budget_avg":0,"descryption":"","completed":false,"memo":"","title":"전입신고","__v":0}
{"_id":{"$oid":"599698a3c72cb0674180722a"},"ownerid":"599698a3c72cb0674180719c","categoryid":"599698a3c72cb0674180719e","budget":0,"budget_avg":0,"descryption":"","completed":false,"memo":"","title":"전기가입","__v":0}
{"_id":{"$oid":"599698a3c72cb0674180722b"},"ownerid":"599698a3c72cb0674180719c","categoryid":"599698a3c72cb0674180719e","budget":0,"budget_avg":0,"descryption":"","completed":false,"memo":"","title":"인터넷 가입 및 설치","__v":0}
{"_id":{"$oid":"599698a3c72cb0674180722c"},"ownerid":"599698a3c72cb0674180719c","categoryid":"599698a3c72cb0674180719e","budget":0,"budget_avg":0,"descryption":"","completed":false,"memo":"","title":"경제조건 및 직장위치 고려해 신혼집결정","__v":0}
{"_id":{"$oid":"599698a3c72cb0674180722d"},"ownerid":"599698a3c72cb0674180719c","categoryid":"599698a3c72cb0674180719e","budget":0,"budget_avg":0,"descryption":"","completed":false,"memo":"","title":"예산 수립","__v":0}
{"_id":{"$oid":"599698a3c72cb0674180722e"},"ownerid":"599698a3c72cb0674180719c","categoryid":"599698a3c72cb0674180719e","budget":0,"budget_avg":0,"descryption":"","completed":false,"memo":"","title":"신혼집 계약(등기부등본확인)","__v":0}
{"_id":{"$oid":"599698a3c72cb0674180722f"},"ownerid":"599698a3c72cb0674180719c","categoryid":"599698a3c72cb0674180719e","budget":0,"budget_avg":0,"descryption":"","completed":false,"memo":"","title":"신혼집 꾸미기","__v":0}
{"_id":{"$oid":"599698a3c72cb06741807230"},"ownerid":"599698a3c72cb0674180719c","categoryid":"599698a3c72cb0674180719f","budget":0,"budget_avg":0,"descryption":"","completed":false,"memo":"","title":"약혼발표 및 방법 가족과 논의","__v":0}
{"_id":{"$oid":"599698a3c72cb06741807231"},"ownerid":"599698a3c72cb0674180719c","categoryid":"599698a3c72cb0674180719f","budget":0,"budget_avg":0,"descryption":"","completed":false,"memo":"","title":"약혼일 택일","__v":0}
{"_id":{"$oid":"599698a3c72cb06741807232"},"ownerid":"599698a3c72cb0674180719c","categoryid":"599698a3c72cb0674180719f","budget":0,"budget_avg":0,"descryption":"","completed":false,"memo":"","title":"약혼식 참석자확인","__v":0}
{"_id":{"$oid":"599698a3c72cb06741807233"},"ownerid":"599698a3c72cb0674180719c","categoryid":"599698a3c72cb0674180719f","budget":100,"budget_avg":0,"descryption":"","completed":false,"memo":"","title":"약혼장소 예약","__v":0}
{"_id":{"$oid":"599698a3c72cb06741807234"},"ownerid":"599698a3c72cb0674180719c","categoryid":"599698a3c72cb0674180719f","budget":101,"budget_avg":0,"descryption":"","completed":false,"memo":"","title":"예산 수립","__v":0}
{"_id":{"$oid":"599698a3c72cb06741807235"},"ownerid":"599698a3c72cb0674180719c","categoryid":"599698a3c72cb067418071a0","budget":0,"budget_avg":0,"descryption":"","completed":false,"memo":"","title":"결혼식 진행방식 결정","__v":0}
{"_id":{"$oid":"599698a3c72cb06741807236"},"ownerid":"599698a3c72cb0674180719c","categoryid":"599698a3c72cb067418071ac","budget":0,"budget_avg":0,"descryption":"","completed":false,"memo":"","title":"예산 수립","__v":0}
{"_id":{"$oid":"599698a3c72cb06741807237"},"ownerid":"599698a3c72cb0674180719c","categoryid":"599698a3c72cb067418071ac","budget":0,"budget_avg":0,"descryption":"","completed":false,"memo":"","title":"구매 할 것인지 빌릴것인지 결정","__v":0}
{"_id":{"$oid":"599698a3c72cb06741807238"},"ownerid":"599698a3c72cb0674180719c","categoryid":"599698a3c72cb067418071ac","budget":0,"budget_avg":0,"descryption":"","completed":false,"memo":"","title":"신랑 한복","__v":0}
{"_id":{"$oid":"599698a3c72cb06741807239"},"ownerid":"599698a3c72cb0674180719c","categoryid":"599698a3c72cb067418071ac","budget":0,"budget_avg":0,"descryption":"","completed":false,"memo":"","title":"신부 한복","__v":0}
{"_id":{"$oid":"599698a3c72cb0674180723a"},"ownerid":"599698a3c72cb0674180719c","categoryid":"599698a3c72cb067418071ac","budget":0,"budget_avg":0,"descryption":"","completed":false,"memo":"","title":"신랑 어머니 한복","__v":0}
{"_id":{"$oid":"599698a3c72cb0674180723b"},"ownerid":"599698a3c72cb0674180719c","categoryid":"599698a3c72cb067418071ac","budget":0,"budget_avg":0,"descryption":"","completed":false,"memo":"","title":"신부 어머니 한복","__v":0}
{"_id":{"$oid":"599698a3c72cb0674180723c"},"ownerid":"599698a3c72cb0674180719c","categoryid":"599698a3c72cb067418071ac","budget":0,"budget_avg":0,"descryption":"","completed":false,"memo":"","title":"신랑 아버지 양장","__v":0}
{"_id":{"$oid":"599698a3c72cb0674180723d"},"ownerid":"599698a3c72cb0674180719c","categoryid":"599698a3c72cb067418071ac","budget":0,"budget_avg":0,"descryption":"","completed":false,"memo":"","title":"신부 아버지 양장","__v":0}
{"_id":{"$oid":"599698a3c72cb0674180723e"},"ownerid":"599698a3c72cb0674180719c","categoryid":"599698a3c72cb067418071ad","budget":100,"budget_avg":10,"descryption":"","completed":false,"memo":"","title":"예산 및 계획 수립","__v":0}
{"_id":{"$oid":"599698a3c72cb0674180723f"},"ownerid":"599698a3c72cb0674180719c","categoryid":"599698a3c72cb067418071ac","budget":0,"budget_avg":0,"descryption":"","completed":false,"memo":"","title":"시장 조사","__v":0}
{"_id":{"$oid":"599698a3c72cb06741807240"},"ownerid":"599698a3c72cb0674180719c","categoryid":"599698a3c72cb067418071ac","budget":0,"budget_avg":0,"descryption":"","completed":false,"memo":"","title":"신랑 예복","__v":0}
{"_id":{"$oid":"599698a3c72cb06741807241"},"ownerid":"599698a3c72cb0674180719c","categoryid":"599698a3c72cb067418071ac","budget":0,"budget_avg":0,"descryption":"","completed":false,"memo":"","title":"신부 예복","__v":0}
{"_id":{"$oid":"599698a3c72cb06741807242"},"ownerid":"599698a3c72cb0674180719c","categoryid":"599698a3c72cb067418071a2","budget":0,"budget_avg":0,"descryption":"","completed":false,"memo":"","title":"신혼살림 들이기","__v":0}
{"_id":{"$oid":"599698a3c72cb06741807243"},"ownerid":"599698a3c72cb0674180719c","categoryid":"599698a3c72cb067418071ad","budget":0,"budget_avg":0,"descryption":"","completed":false,"memo":"","title":"신랑 피부관리","__v":0}
{"_id":{"$oid":"599698a3c72cb06741807244"},"ownerid":"599698a3c72cb0674180719c","categoryid":"599698a3c72cb067418071ad","budget":0,"budget_avg":0,"descryption":"","completed":false,"memo":"","title":"신부 피부관리","__v":0}
{"_id":{"$oid":"599698a3c72cb06741807245"},"ownerid":"599698a3c72cb0674180719c","categoryid":"599698a3c72cb067418071a3","budget":0,"budget_avg":0,"descryption":"","completed":false,"memo":"","title":"함 준비","__v":0}
{"_id":{"$oid":"599698a3c72cb06741807246"},"ownerid":"599698a3c72cb0674180719c","categoryid":"599698a3c72cb067418071a3","budget":0,"budget_avg":0,"descryption":"","completed":false,"memo":"","title":"함 지기 섭외","__v":0}
{"_id":{"$oid":"599698a3c72cb06741807247"},"ownerid":"599698a3c72cb0674180719c","categoryid":"599698a3c72cb067418071a2","budget":0,"budget_avg":0,"descryption":"","completed":false,"memo":"","title":"신랑 신부가 쓰던 것 중 들일 것 확인","__v":0}
{"_id":{"$oid":"599698a3c72cb06741807248"},"ownerid":"599698a3c72cb0674180719c","categoryid":"599698a3c72cb067418071a2","budget":0,"budget_avg":0,"descryption":"","completed":false,"memo":"","title":"선물로 받을것 목록 작성","__v":0}
